fattura_elettronica_reader/__init__.py
fattura_elettronica_reader/__main__.py
fattura_elettronica_reader/api.py
fattura_elettronica_reader/cli.py
fattura_elettronica_reader/constants.py
fattura_elettronica_reader/exceptions.py
fattura_elettronica_reader-3.0.5.dist-info/LICENSE.txt
fattura_elettronica_reader-3.0.5.dist-info/METADATA
fattura_elettronica_reader-3.0.5.dist-info/WHEEL
fattura_elettronica_reader-3.0.5.dist-info/entry_points.txt
fattura_elettronica_reader-3.0.5.dist-info/top_level.txt
fattura_elettronica_reader-3.0.5.dist-info/RECORD
