Metadata-Version: 2.1
Name: fattura-elettronica-reader
Version: 3.0.5
Summary: Check and extract electronic invoices received from the Sistema di Interscambio
Home-page: https://blog.franco.net.eu.org/software/#fattura-elettronica-reader
Author: Franco Masotti
Author-email: franco.masotti@tutanota.com
License: GPLv3+,
Keywords: invoice,reader,SDI
Classifier: Development Status :: 2 - Pre-Alpha
Classifier: Topic :: Utilities
Classifier: Intended Audience :: End Users/Desktop
Classifier: Environment :: Console
Classifier: License :: OSI Approved :: GNU General Public License v3 or later (GPLv3+)
Classifier: Programming Language :: Python :: 3
Requires-Python: <4,>=3.5
License-File: LICENSE.txt
